{
  "name": "Home",
  "path": "/example-path",
  "sections": [
    {
      "__resolveType": "website/flags/multivariate/section.ts",
      "variants": [
        {
          "value": {
            "__resolveType": "site/sections/Hero.tsx",
            "title": "<p><strong><span style=\"font-size: 64pt\">AI-Powered Task Scheduling Chatbot</span></strong></p><p></p><p></p>",
            "placement": "left",
            "cta": []
          },
          "rule": {
            "__resolveType": "website/matchers/always.ts"
          }
        }
      ]
    }
  ],
  "seo": {
    "__resolveType": "website/sections/Seo/SeoV2.tsx"
  },
  "__resolveType": "website/pages/Page.tsx"
}